README.rst
setup.py
bin/onlinectl
onlinectl/__init__.py
onlinectl.egg-info/PKG-INFO
onlinectl.egg-info/SOURCES.txt
onlinectl.egg-info/dependency_links.txt
onlinectl.egg-info/not-zip-safe
onlinectl.egg-info/requires.txt
onlinectl.egg-info/top_level.txt