Metadata-Version: 1.0
Name: onlinectl
Version: 0.7
Summary: CLI to manage your online.net account
Home-page: https://github.com/Krast76/onlinectl
Author: Ludovic Logiou
Author-email: ludovic.logiou@gmail.com
License: MIT
Platform: UNKNOWN
